LICENSE
MANIFEST.in
README.md
setup.py
topsis_101703325.egg-info/PKG-INFO
topsis_101703325.egg-info/SOURCES.txt
topsis_101703325.egg-info/dependency_links.txt
topsis_101703325.egg-info/entry_points.txt
topsis_101703325.egg-info/requires.txt
topsis_101703325.egg-info/top_level.txt
topsis_python/topsis.py