Metadata-Version: 2.1
Name: topsis-101703325
Version: 1.0.0
Summary: A Python package implementing TOPSIS technique.
Home-page: UNKNOWN
Author: Maninder Singh
Author-email: manii.sandhuu@gmail.com
License: MIT
Platform: UNKNOWN
Classifier: License :: OSI Approved :: MIT License
Classifier: Programming Language :: Python :: 3
Classifier: Programming Language :: Python :: 3.7
